.gitignore
LICENSE
MANIFEST.in
README.md
pyproject.toml
setup.py
vcp_tools.sh
bin/vcp
tests/requirements.txt
tests/test_core.py
tests/test_system_package_manager_handlers.py
vcp/__init__.py
vcp/box.py
vcp/box_renderer.py
vcp/cli_arguments_tree_parser.py
vcp/colors.py
vcp/commands.py
vcp/exceptions.py
vcp/language_environments.py
vcp/packages.py
vcp/project.py
vcp/project_handler_base.py
vcp/project_handlers.py
vcp/project_languages.py
vcp/repositories.py
vcp/repository.py
vcp/repository_command_result_box.py
vcp/setup_py_template.py
vcp/system_package_manager_handlers.py
vcp/tools.py
vcp/version.py
vcp.egg-info/PKG-INFO
vcp.egg-info/SOURCES.txt
vcp.egg-info/dependency_links.txt
vcp.egg-info/requires.txt
vcp.egg-info/top_level.txt