Metadata-Version: 1.0
Name: vcp
Version: 3.0.0
Summary: Version Control Projects - organize repositories
Home-page: https://github.com/voidpp/vcp.git
Author: Lajos Santa
Author-email: santa.lajos@gmail.com
License: MIT
Platform: UNKNOWN
